<dsxout>
	<s>117</s>
	<copyright>Admedia / dsX xml output COPYRIGHT 1999-2012 Admedia, Inc. (http://www.admedia.com/) All rights reserved. vc3.17</copyright>
	<searchinfo>
		<terms>cat videos</terms>
		<country>US</country>
		<hitcount>10</hitcount>
		<first>1</first>
		<last>10</last>
	</searchinfo>
	<results>
		<listing>
			<title>Looking for Cat Videos?</title>
			<url>www.LocalDouble.com</url>
			<favicon/>
			<redirect>http://redir.localpages.com/r1.php?h=eebd4890f4ebb62f3b39233b8d7f796e&s=c&px=1&mm=1&wf=1&ai=16903&fm=2275&st=cat+videos&tos=1331939956&mca=0</redirect>
			<description>Get Numbers, Addresses, Directions, Ratings & Other Local Info.</description>
			<bid>0.1</bid>
			<img>http://images.colo.com/x/ar7.jpg</img>
		</listing>
<listing><title>Looking for Cat Video</title><url>www.Compare.us</url><favicon/><redirect>http://click.debsfupages.com/r1.php?h=0330e5033886cbdd84748c25c63fc3e4&s=c&px=1&mm=1&wf=1&ai=16903&fm=2&st=cat+videos&tos=1331939956&mca=0</redirect><description>Find, Compare & Review offers from top brands at Compare.US.</description><bid>0.03</bid><img>http://images.colo.com/x/ar5.jpg</img></listing><listing><title>FREE Movies</title><url>W-ebs.org/Movies</url><favicon/><redirect>http://click.debsfupages.com/r1.php?h=2eda94638d7a7ac795c2c06d01bf861e&s=c&px=1&mm=1&wf=1&ai=16903&fm=2&st=cat+videos&tos=1331939956&mca=0</redirect><description>Get Here The Best Movies Online ...</description><bid>0.015</bid><img>http://images.colo.com/x/ar6.jpg</img></listing><listing><title>Click for the top Cat Video sites</title><url>www.ASK.com</url><favicon>http://favicon.colo.com/006e85335fb0aec7cc9038fa738a161e.jpg</favicon><redirect>http://click.debsfupages.com/r1.php?h=a89cb41cf3aa0570c08243c331b8b0ee&s=c&px=1&mm=1&wf=1&ai=16903&fm=2&st=cat+videos&tos=1331939956&mca=0</redirect><description>Find the right Cat Video sites at ask.com</description><bid>0.005</bid><img>http://images.colo.com/x/ar4.jpg</img></listing><listing><title>* Free Xbox 360 with Kinect *</title><url>www.xboxkinect.com</url><favicon/><redirect>http://click.debsfupages.com/r1.php?h=0d35264583405c3c169fa28a0ffe1702&s=c&px=1&mm=1&wf=1&ai=16903&fm=2&st=cat+videos&tos=1331939956&mca=0</redirect><description>enter your email for a chance to win the Xbox 360 with Kinect. Cash in on the hottest gaming system on the market. Only today for U.S residents</description><bid>0.005</bid><img>http://images.colo.com/x/ar3.jpg</img></listing><listing><title>The Beast of Gevaudan</title><url>www.cryptozoologysociety.com</url><favicon/><redirect>http://click.debsfupages.com/r1.php?h=2dafbdd75a5ec4d2d9c792e7bf81a01d&s=c&px=1&mm=1&wf=1&ai=16903&fm=2&st=cat+videos&tos=1331939956&mca=0</redirect><description>The Beast of Gevaudan is a name given to man-eating cat-like animals alleged to have terrorized France. The beasts were described having formidable teeth and immense tails.</description><bid>0.005</bid><img>http://images.colo.com/x/ar1.jpg</img></listing><listing><title>Bigfoot Video</title><url>www.cryptozoologysociety.com/</url><favicon/><redirect>http://click.debsfupages.com/r1.php?h=48372fba687333af7f41ea06e50f95cf&s=c&px=1&mm=1&wf=1&ai=16903&fm=2&st=cat+videos&tos=1331939956&mca=0</redirect><description>Free Bigfoot video. Real footage of Bigfoot including the 1967 Patterson film. Free membership to the Crytozoology Society.</description><bid>0.005</bid><img>http://images.colo.com/x/ar2.jpg</img></listing><listing><title>$250 Petsmart Gift Card</title><url>www.savvygiftrewards.com</url><favicon/><redirect>http://click.debsfupages.com/r1.php?h=cec294bd318ee79e4c27e6c03801c91f&s=c&px=1&mm=1&wf=1&ai=16903&fm=2&st=cat+videos&tos=1331939956&mca=0</redirect><description>Get a free $250 Petsmart gift card!</description><bid>0.005</bid><img>http://images.colo.com/x/ar7.jpg</img></listing><listing><title>Find it at Cheapstuff.com</title><url>cheapstuff.com</url><favicon>http://favicon.colo.com/34383eff6d48347eff661b5d333d6a5b.jpg</favicon><redirect>http://click.debsfupages.com/r1.php?h=74e7506f7d6b982f791e72b2ef81ec64&s=c&px=1&mm=1&wf=1&ai=16903&fm=2&st=cat+videos&tos=1331939956&mca=0</redirect><description>Looking for cat video? Find it at Cheapstuff.com</description><bid>0.005</bid><img>http://images.colo.com/x/ar7.jpg</img></listing><listing><title>Find it at Items.com</title><url>items.com</url><favicon>http://favicon.colo.com/b2ec794577bde449979a12fc1ec701ae.jpg</favicon><redirect>http://click.debsfupages.com/r1.php?h=f5734977ad28d9d6a14b37c4160c23ab&s=c&px=1&mm=1&wf=1&ai=16903&fm=2&st=cat+videos&tos=1331939956&mca=0</redirect><description>Looking for cat video? Find it at Items.com</description><bid>0.005</bid><img>http://images.colo.com/x/ar7.jpg</img></listing></results><pixel><img src=http://iar.worthathousandwords.com/iar.gif?pid=6235.16903 width="0" height="0"><img src=http://track.colo.com/p/pt.php?aid=16903 width="0" height="0"></pixel><process>0.70893692970276</process><parse>0.64107990264893</parse>
</dsxout>